{"version":"3.11.0","examples":[{"id":"./spec/models/mission_spec.rb[1:1:1]","description":"can access the associated scientist","full_description":"Mission relationships can access the associated scientist","status":"passed","file_path":"./spec/models/mission_spec.rb","line_number":10,"run_time":0.01316,"pending_message":null},{"id":"./spec/models/mission_spec.rb[1:1:2]","description":"can access the associated planet","full_description":"Mission relationships can access the associated planet","status":"passed","file_path":"./spec/models/mission_spec.rb","line_number":16,"run_time":0.002392,"pending_message":null},{"id":"./spec/models/mission_spec.rb[1:2:1]","description":"must have a name","full_description":"Mission validations must have a name","status":"passed","file_path":"./spec/models/mission_spec.rb","line_number":26,"run_time":0.003825,"pending_message":null},{"id":"./spec/models/mission_spec.rb[1:2:2]","description":"must have a scientist","full_description":"Mission validations must have a scientist","status":"passed","file_path":"./spec/models/mission_spec.rb","line_number":31,"run_time":0.002914,"pending_message":null},{"id":"./spec/models/mission_spec.rb[1:2:3]","description":"must have a planet","full_description":"Mission validations must have a planet","status":"passed","file_path":"./spec/models/mission_spec.rb","line_number":36,"run_time":0.00313,"pending_message":null},{"id":"./spec/models/mission_spec.rb[1:2:4]","description":"must not allow a scientist to join the same mission twice","full_description":"Mission validations must not allow a scientist to join the same mission twice","status":"passed","file_path":"./spec/models/mission_spec.rb","line_number":41,"run_time":0.003398,"pending_message":null},{"id":"./spec/models/planet_spec.rb[1:1:1]","description":"can access the associated missions","full_description":"Planet relationships can access the associated missions","status":"passed","file_path":"./spec/models/planet_spec.rb","line_number":10,"run_time":0.006276,"pending_message":null},{"id":"./spec/models/planet_spec.rb[1:1:2]","description":"can access the associated scientist","full_description":"Planet relationships can access the associated scientist","status":"passed","file_path":"./spec/models/planet_spec.rb","line_number":16,"run_time":0.006,"pending_message":null},{"id":"./spec/models/scientist_spec.rb[1:1:1]","description":"can access the associated missions","full_description":"Scientist relationships can access the associated missions","status":"passed","file_path":"./spec/models/scientist_spec.rb","line_number":9,"run_time":0.002984,"pending_message":null},{"id":"./spec/models/scientist_spec.rb[1:1:2]","description":"can access the associated planets","full_description":"Scientist relationships can access the associated planets","status":"passed","file_path":"./spec/models/scientist_spec.rb","line_number":15,"run_time":0.00282,"pending_message":null},{"id":"./spec/models/scientist_spec.rb[1:2:1]","description":"must have a name","full_description":"Scientist validations must have a name","status":"passed","file_path":"./spec/models/scientist_spec.rb","line_number":24,"run_time":0.00191,"pending_message":null},{"id":"./spec/models/scientist_spec.rb[1:2:2]","description":"must have a field_of_study","full_description":"Scientist validations must have a field_of_study","status":"passed","file_path":"./spec/models/scientist_spec.rb","line_number":29,"run_time":0.001836,"pending_message":null},{"id":"./spec/models/scientist_spec.rb[1:2:3]","description":"must have a unique name","full_description":"Scientist validations must have a unique name","status":"passed","file_path":"./spec/models/scientist_spec.rb","line_number":34,"run_time":0.001544,"pending_message":null},{"id":"./spec/requests/missions_spec.rb[1:1:1:1]","description":"creates a new Mission","full_description":"Missions POST /missions with valid data creates a new Mission","status":"passed","file_path":"./spec/requests/missions_spec.rb","line_number":17,"run_time":0.024177,"pending_message":null},{"id":"./spec/requests/missions_spec.rb[1:1:1:2]","description":"returns the associated Planet data","full_description":"Missions POST /missions with valid data returns the associated Planet data","status":"passed","file_path":"./spec/requests/missions_spec.rb","line_number":21,"run_time":0.006921,"pending_message":null},{"id":"./spec/requests/missions_spec.rb[1:1:1:3]","description":"returns a status code of 201 (created)","full_description":"Missions POST /missions with valid data returns a status code of 201 (created)","status":"passed","file_path":"./spec/requests/missions_spec.rb","line_number":32,"run_time":0.005477,"pending_message":null},{"id":"./spec/requests/missions_spec.rb[1:1:2:1]","description":"does not creates a new Mission","full_description":"Missions POST /missions with invalid data does not creates a new Mission","status":"passed","file_path":"./spec/requests/missions_spec.rb","line_number":42,"run_time":0.526857,"pending_message":null},{"id":"./spec/requests/missions_spec.rb[1:1:2:2]","description":"returns the error messages","full_description":"Missions POST /missions with invalid data returns the error messages","status":"passed","file_path":"./spec/requests/missions_spec.rb","line_number":46,"run_time":0.00805,"pending_message":null},{"id":"./spec/requests/missions_spec.rb[1:1:2:3]","description":"returns a status code of 422 (Unprocessable Entity)","full_description":"Missions POST /missions with invalid data returns a status code of 422 (Unprocessable Entity)","status":"passed","file_path":"./spec/requests/missions_spec.rb","line_number":54,"run_time":0.00699,"pending_message":null},{"id":"./spec/requests/planets_spec.rb[1:1:1]","description":"returns an array of all planets","full_description":"Planets GET /index returns an array of all planets","status":"passed","file_path":"./spec/requests/planets_spec.rb","line_number":11,"run_time":0.007853,"pending_message":null},{"id":"./spec/requests/planets_spec.rb[1:1:2]","description":"returns a status of 200 (OK)","full_description":"Planets GET /index returns a status of 200 (OK)","status":"passed","file_path":"./spec/requests/planets_spec.rb","line_number":32,"run_time":0.005064,"pending_message":null},{"id":"./spec/requests/scientists_spec.rb[1:1:1]","description":"returns an array of all scientists","full_description":"Scientists GET /index returns an array of all scientists","status":"passed","file_path":"./spec/requests/scientists_spec.rb","line_number":15,"run_time":0.013456,"pending_message":null},{"id":"./spec/requests/scientists_spec.rb[1:1:2]","description":"returns a status of 200 (OK)","full_description":"Scientists GET /index returns a status of 200 (OK)","status":"passed","file_path":"./spec/requests/scientists_spec.rb","line_number":34,"run_time":0.009876,"pending_message":null},{"id":"./spec/requests/scientists_spec.rb[1:2:1:1]","description":"returns the matching scientist with their associated planets","full_description":"Scientists GET /scientists/:id with a valid ID returns the matching scientist with their associated planets","status":"passed","file_path":"./spec/requests/scientists_spec.rb","line_number":44,"run_time":0.012693,"pending_message":null},{"id":"./spec/requests/scientists_spec.rb[1:2:1:2]","description":"returns a status of 200 (OK)","full_description":"Scientists GET /scientists/:id with a valid ID returns a status of 200 (OK)","status":"passed","file_path":"./spec/requests/scientists_spec.rb","line_number":70,"run_time":0.008929,"pending_message":null},{"id":"./spec/requests/scientists_spec.rb[1:2:2:1]","description":"returns an error message","full_description":"Scientists GET /scientists/:id with an invalid ID returns an error message","status":"passed","file_path":"./spec/requests/scientists_spec.rb","line_number":79,"run_time":0.007701,"pending_message":null},{"id":"./spec/requests/scientists_spec.rb[1:2:2:2]","description":"returns the appropriate HTTP status code","full_description":"Scientists GET /scientists/:id with an invalid ID returns the appropriate HTTP status code","status":"passed","file_path":"./spec/requests/scientists_spec.rb","line_number":86,"run_time":0.00667,"pending_message":null},{"id":"./spec/requests/scientists_spec.rb[1:3:1:1]","description":"creates a new Scientist","full_description":"Scientists POST /scientists with valid data creates a new Scientist","status":"passed","file_path":"./spec/requests/scientists_spec.rb","line_number":99,"run_time":0.007985,"pending_message":null},{"id":"./spec/requests/scientists_spec.rb[1:3:1:2]","description":"returns the associated Scientist data","full_description":"Scientists POST /scientists with valid data returns the associated Scientist data","status":"passed","file_path":"./spec/requests/scientists_spec.rb","line_number":103,"run_time":0.008413,"pending_message":null},{"id":"./spec/requests/scientists_spec.rb[1:3:1:3]","description":"returns a status code of 201 (created)","full_description":"Scientists POST /scientists with valid data returns a status code of 201 (created)","status":"passed","file_path":"./spec/requests/scientists_spec.rb","line_number":113,"run_time":0.007113,"pending_message":null},{"id":"./spec/requests/scientists_spec.rb[1:3:2:1]","description":"does not creates a new Scientist","full_description":"Scientists POST /scientists with invalid data does not creates a new Scientist","status":"passed","file_path":"./spec/requests/scientists_spec.rb","line_number":123,"run_time":0.011287,"pending_message":null},{"id":"./spec/requests/scientists_spec.rb[1:3:2:2]","description":"returns the error messages","full_description":"Scientists POST /scientists with invalid data returns the error messages","status":"passed","file_path":"./spec/requests/scientists_spec.rb","line_number":127,"run_time":0.013004,"pending_message":null},{"id":"./spec/requests/scientists_spec.rb[1:3:2:3]","description":"returns a status code of 422 (Unprocessable Entity)","full_description":"Scientists POST /scientists with invalid data returns a status code of 422 (Unprocessable Entity)","status":"passed","file_path":"./spec/requests/scientists_spec.rb","line_number":135,"run_time":0.011303,"pending_message":null},{"id":"./spec/requests/scientists_spec.rb[1:4:1:1]","description":"returns the associated Scientist data","full_description":"Scientists PATCH /scientists with valid data returns the associated Scientist data","status":"passed","file_path":"./spec/requests/scientists_spec.rb","line_number":150,"run_time":0.008982,"pending_message":null},{"id":"./spec/requests/scientists_spec.rb[1:4:1:2]","description":"returns a status code of 202 (accepted)","full_description":"Scientists PATCH /scientists with valid data returns a status code of 202 (accepted)","status":"passed","file_path":"./spec/requests/scientists_spec.rb","line_number":160,"run_time":0.00817,"pending_message":null},{"id":"./spec/requests/scientists_spec.rb[1:4:2:1]","description":"returns the error messages","full_description":"Scientists PATCH /scientists with invalid data returns the error messages","status":"passed","file_path":"./spec/requests/scientists_spec.rb","line_number":170,"run_time":0.00886,"pending_message":null},{"id":"./spec/requests/scientists_spec.rb[1:4:2:2]","description":"returns a status code of 422 (Unprocessable Entity)","full_description":"Scientists PATCH /scientists with invalid data returns a status code of 422 (Unprocessable Entity)","status":"passed","file_path":"./spec/requests/scientists_spec.rb","line_number":178,"run_time":0.008928,"pending_message":null},{"id":"./spec/requests/scientists_spec.rb[1:4:3:1]","description":"returns the error message","full_description":"Scientists PATCH /scientists with invalid ID returns the error message","status":"passed","file_path":"./spec/requests/scientists_spec.rb","line_number":190,"run_time":0.007484,"pending_message":null},{"id":"./spec/requests/scientists_spec.rb[1:4:3:2]","description":"returns the appropriate HTTP status code","full_description":"Scientists PATCH /scientists with invalid ID returns the appropriate HTTP status code","status":"passed","file_path":"./spec/requests/scientists_spec.rb","line_number":197,"run_time":0.009711,"pending_message":null},{"id":"./spec/requests/scientists_spec.rb[1:5:1:1]","description":"deletes the Scientist","full_description":"Scientists DELETE /scientists/:id with a valid ID deletes the Scientist","status":"passed","file_path":"./spec/requests/scientists_spec.rb","line_number":210,"run_time":0.011498,"pending_message":null},{"id":"./spec/requests/scientists_spec.rb[1:5:1:2]","description":"deletes the associated Missions","full_description":"Scientists DELETE /scientists/:id with a valid ID deletes the associated Missions","status":"passed","file_path":"./spec/requests/scientists_spec.rb","line_number":214,"run_time":0.010712,"pending_message":null},{"id":"./spec/requests/scientists_spec.rb[1:5:2:1]","description":"returns an error message","full_description":"Scientists DELETE /scientists/:id with an invalid ID returns an error message","status":"passed","file_path":"./spec/requests/scientists_spec.rb","line_number":223,"run_time":0.006743,"pending_message":null},{"id":"./spec/requests/scientists_spec.rb[1:5:2:2]","description":"returns the appropriate HTTP status code","full_description":"Scientists DELETE /scientists/:id with an invalid ID returns the appropriate HTTP status code","status":"passed","file_path":"./spec/requests/scientists_spec.rb","line_number":231,"run_time":0.006031,"pending_message":null},{"id":"./spec/routing/unnecessary_routes_spec.rb[1:1]","description":"does not define unnecessary planets routes","full_description":"UnnecessaryRoutes does not define unnecessary planets routes","status":"passed","file_path":"./spec/routing/unnecessary_routes_spec.rb","line_number":5,"run_time":0.00037,"pending_message":null},{"id":"./spec/routing/unnecessary_routes_spec.rb[1:2]","description":"does not define unnecessary missions routes","full_description":"UnnecessaryRoutes does not define unnecessary missions routes","status":"passed","file_path":"./spec/routing/unnecessary_routes_spec.rb","line_number":12,"run_time":0.000259,"pending_message":null}],"summary":{"duration":0.855651,"example_count":45,"failure_count":0,"pending_count":0,"errors_outside_of_examples_count":0},"summary_line":"45 examples, 0 failures"}